hgdemo/__init__.py
hgdemo/circle.py
hgdemo/square.py
hgdemo-0.0.1.dist-info/LICENSE
hgdemo-0.0.1.dist-info/METADATA
hgdemo-0.0.1.dist-info/WHEEL
hgdemo-0.0.1.dist-info/top_level.txt
hgdemo-0.0.1.dist-info/RECORD
