Metadata-Version: 2.1
Name: hgdemo
Version: 0.0.1
Summary: Learning how to post python packages in PyPi, github, ReadtheDocs
Home-page: https://github.com/Gurgenci/hgdemo
Author: Hal Gurgenci
Author-email: h.gurgenci@uq.edu.au
License: UNKNOWN
Platform: UNKNOWN
Classifier: Programming Language :: Python :: 3
Classifier: License :: OSI Approved :: MIT License
Classifier: Operating System :: OS Independent
Requires-Python: >=3.0
License-File: LICENSE
